HierarTree/__init__.py
HierarTree/tree_classifier.py
HierarTree-0.1.dist-info/METADATA
HierarTree-0.1.dist-info/WHEEL
HierarTree-0.1.dist-info/top_level.txt
HierarTree-0.1.dist-info/RECORD
