Metadata-Version: 2.1
Name: HierarTree
Version: 0.1
Summary: A Python package for hierarchical decision tree and random forest classifiers
Home-page: https://github.com/lbiral/HierarTree
Author: Leonardo Biral
Author-email: leonardo.biral@duke.edu
License: UNKNOWN
Platform: UNKNOWN
Classifier: Programming Language :: Python :: 3
Classifier: License :: OSI Approved :: MIT License
Classifier: Operating System :: OS Independent
Requires-Python: >=3.6
Requires-Dist: numpy
Requires-Dist: pandas
Requires-Dist: matplotlib
Requires-Dist: joblib
Requires-Dist: sklearn
